tj_odd_or_even/__init__.py
tj_odd_or_even/checker.py
tj_odd_or_even_checker-0.1.0.dist-info/licenses/LICENSE
tj_odd_or_even_checker-0.1.0.dist-info/METADATA
tj_odd_or_even_checker-0.1.0.dist-info/WHEEL
tj_odd_or_even_checker-0.1.0.dist-info/top_level.txt
tj_odd_or_even_checker-0.1.0.dist-info/RECORD
