Metadata-Version: 2.4
Name: tj_odd_or_even-checker
Version: 0.1.0
Summary: A simple library to check odd or even numbers.
Author-email: Treesa Jose <2treesajo@gmail.com>
License: MIT License
Keywords: odd,even,numbers
Classifier: Programming Language :: Python :: 3
Classifier: License :: OSI Approved :: MIT License
Classifier: Operating System :: OS Independent
Requires-Python: >=3.7
License-File: LICENSE
Dynamic: license-file
